pong_arcade/__init__.py
pong_arcade/ball.py
pong_arcade/main.py
pong_arcade/meta.py
pong_arcade/player.py
pong_arcade/pong.py
pong_arcade/data/gfx/atari.otf
pong_arcade/data/gfx/logo.png
pong_arcade/data/sfx/paddle.wav
pong_arcade/data/sfx/score.wav
pong_arcade/data/sfx/wall.wav
pong_arcade-2.5.4.dist-info/METADATA
pong_arcade-2.5.4.dist-info/WHEEL
pong_arcade-2.5.4.dist-info/entry_points.txt
pong_arcade-2.5.4.dist-info/licenses/LICENSE
pong_arcade-2.5.4.dist-info/RECORD
