Metadata-Version: 2.4
Name: pong-arcade
Version: 2.5.4
Summary: Pong written using pygame
Project-URL: Homepage, https://github.com/jacob-thompson/pong-arcade
Project-URL: Bug Reports, https://github.com/jacob-thompson/pong-arcade/issues
Author-email: "Jacob A. Thompson" <jacobalthompson@gmail.com>
Maintainer-email: "Jacob A. Thompson" <jacobalthompson@gmail.com>
License: MIT License
License-File: LICENSE
Keywords: application,arcade,executable,game,pong
Classifier: Development Status :: 5 - Production/Stable
Classifier: License :: OSI Approved :: MIT License
Classifier: Programming Language :: Python :: 3
Classifier: Programming Language :: Python :: 3 :: Only
Classifier: Programming Language :: Python :: 3.7
Classifier: Programming Language :: Python :: 3.8
Classifier: Programming Language :: Python :: 3.9
Classifier: Programming Language :: Python :: 3.10
Classifier: Programming Language :: Python :: 3.11
Classifier: Programming Language :: Python :: 3.12
Classifier: Programming Language :: Python :: 3.13
Classifier: Topic :: Games/Entertainment
Requires-Python: >=3.7
Requires-Dist: pygame
